initial_avatars/__init__.py
initial_avatars/compat.py
initial_avatars/generator.py
initial_avatars/models.py
initial_avatars/urls.py
initial_avatars/utils.py
initial_avatars/views.py
initial_avatars/font/UbuntuMono-B.ttf
initial_avatars/migrations/0001_initial.py
initial_avatars/migrations/0002_delete_avatar_with_user.py
initial_avatars/migrations/__init__.py
initial_avatars/templatetags/__init__.py
initial_avatars/templatetags/initialavatar.py
django4_initial_avatars-0.9.1.dist-info/LICENCE
django4_initial_avatars-0.9.1.dist-info/METADATA
django4_initial_avatars-0.9.1.dist-info/WHEEL
django4_initial_avatars-0.9.1.dist-info/top_level.txt
django4_initial_avatars-0.9.1.dist-info/RECORD
