Metadata-Version: 2.2
Name: django4-initial-avatars
Version: 0.9.1
Summary: A simple Django app to get avatars based on username and initials if no gravatars is associated with the email address. Forked from axiome-oss.
Home-page: https://github.com/Urolas/django4-initial-avatars
Author: Sophanna NGOV
Author-email: sophanna.ngov@gmail.com
License: BSD License
Keywords: django avatar gravatar
Classifier: Environment :: Web Environment
Classifier: Framework :: Django
Classifier: Intended Audience :: Developers
Classifier: Development Status :: 4 - Beta
Classifier: License :: OSI Approved :: BSD License
Classifier: Operating System :: OS Independent
Classifier: Programming Language :: Python
Classifier: Programming Language :: Python :: 2.7
Classifier: Programming Language :: Python :: 3.4
Classifier: Programming Language :: Python :: 3.5
Classifier: Programming Language :: Python :: 3.6
Classifier: Framework :: Django :: 1.7
Classifier: Framework :: Django :: 1.8
Classifier: Framework :: Django :: 1.9
Classifier: Framework :: Django :: 1.10
Classifier: Framework :: Django :: 1.11
Classifier: Framework :: Django :: 2.0
Classifier: Framework :: Django :: 4.2
Classifier: Topic :: Internet :: WWW/HTTP
Classifier: Topic :: Internet :: WWW/HTTP :: Dynamic Content
License-File: LICENCE
Requires-Dist: Pillow
Requires-Dist: Django
Provides-Extra: gravatar
Requires-Dist: django-gravatar2>=1.3.0; extra == "gravatar"
Dynamic: author
Dynamic: author-email
Dynamic: classifier
Dynamic: description
Dynamic: description-content-type
Dynamic: home-page
Dynamic: keywords
Dynamic: license
Dynamic: provides-extra
Dynamic: requires-dist
Dynamic: summary
